protocol_mcp/__init__.py
protocol_mcp/config.py
protocol_mcp/main.py
protocol_mcp/mcp.py
protocol_mcp/clients/__init__.py
protocol_mcp/clients/protocols_io.py
protocol_mcp/models/__init__.py
protocol_mcp/models/protocols_io.py
protocol_mcp/services/__init__.py
protocol_mcp/services/protocols_io.py
protocol_mcp/tools/__init__.py
protocol_mcp/tools/_protocols_io.py
protocol_mcp-0.1.2.dist-info/METADATA
protocol_mcp-0.1.2.dist-info/WHEEL
protocol_mcp-0.1.2.dist-info/entry_points.txt
protocol_mcp-0.1.2.dist-info/licenses/LICENSE
protocol_mcp-0.1.2.dist-info/RECORD
